{
  "generatedAt": "2026-07-18T23:44:02Z",
  "brandDir": "/Users/stanchev/Webflow/campaigns-hackathon/design-system-extractor-mine/runs/hubspot-v2/brand",
  "lanes": [
    {
      "lane": "/Users/stanchev/Webflow/campaigns-hackathon/design-system-extractor-mine/experiments/ui-skills-relume-ab/lane-b/index.html",
      "html": "/Users/stanchev/Webflow/campaigns-hackathon/design-system-extractor-mine/experiments/ui-skills-relume-ab/lane-b/index.html",
      "copyCounts": {
        "headings": 6,
        "bodies": 17,
        "eyebrows": 2,
        "ctas": 2
      },
      "checks": [
        {
          "check": "sentence-length",
          "ok": true,
          "detail": "mean 8.8w (max 14), p90 15w (max 23), 20 sentences"
        },
        {
          "check": "exclamations",
          "ok": true,
          "detail": "0 exclamation mark(s) (max 0) \u2014 the measured corpus has none"
        },
        {
          "check": "banned-hype",
          "ok": true,
          "detail": "0 hits across 14-word ban list"
        },
        {
          "check": "heading-casing",
          "ok": true,
          "detail": "6 heading(s) sentence-case (brand terms allowed)"
        }
      ],
      "ok": true
    }
  ]
}