{
  "schemaVersion": "relume-inventory.v1",
  "categories": [
    {
      "slug": "career-sections",
      "name": "Career Sections",
      "components": [
        {"slug": "section_career1", "name": "Career 1", "tags": ["1 Column", "Text Align Center", "Text Align Left", "Accordion", "Buttons", "Job Listings Section"], "preview": "https://cdn.prod.website-files.com/61789b489343c8242282a0ae/61f91cb7f1b3a61eb23734e5_61f919a9b8d04c9bcb54b8fe_image-career1.png"},
        {"slug": "section_career2", "name": "Career 2", "tags": ["1 Column", "Text Align Left", "Accordion", "Buttons", "Job Listings Section"], "preview": "https://cdn.prod.website-files.com/61789b489343c8242282a0ae/61f91cb7ddfecf09c5896fe8_61f919b65e373e6b7be5fa5d_image-career2.png"},
        {"slug": "section_career3", "name": "Career 3", "tags": ["2 Columns", "Text Align Left", "Accordion", "Buttons", "Job Listings Section"], "preview": "https://cdn.prod.website-files.com/61789b489343c8242282a0ae/61f91cb601ef430e59de7361_61f919bf2252d0166ed1084c_image-career3.png"},
        {"slug": "section_career4", "name": "Career 4", "tags": ["1 Column", "Text Align Center", "Text Align Left", "Accordion", "Buttons", "Job Listings Section"], "preview": "https://cdn.prod.website-files.com/61789b489343c8242282a0ae/61f91cb5ddfecfd937896f83_61f919cbf3cc808209576526_image-career4.png"},
        {"slug": "section_career5", "name": "Career 5", "tags": ["1 Column", "Text Align Left", "Accordion", "Buttons", "Job Listings Section"], "preview": "https://cdn.prod.website-files.com/61789b489343c8242282a0ae/61f91cb3f8f7233c41af01af_61f919d872246612abe4269a_image-career5.png"},
        {"slug": "section_career6", "name": "Career 6", "tags": ["2 Columns", "Text Align Left", "Accordion", "Buttons", "Job Listings Section"], "preview": "https://cdn.prod.website-files.com/61789b489343c8242282a0ae/61f91cb101ef43f7d0de7102_61f919e4f2347aa86d54adca_image-career6.png"},
        {"slug": "section_career7", "name": "Career 7", "tags": ["1 Column", "Text Align Center", "Text Align Left", "Accordion", "Buttons", "Job Listings Section"], "preview": "https://cdn.prod.website-files.com/61789b489343c8242282a0ae/61f91cb07e8a23e6f1fdcb96_61f919492799d4dc0ff97814_image-career7.png"},
        {"slug": "section_career8", "name": "Career 8", "tags": ["1 Column", "Text Align Left", "Accordion", "Buttons", "Job Listings Section"], "preview": "https://cdn.prod.website-files.com/61789b489343c8242282a0ae/61f91cac5233c43068a64cc3_61f91956f4bc0f3944183e68_image-career8.png"},
        {"slug": "section_career9", "name": "Career 9", "tags": ["2 Columns", "Text Align Left", "Accordion", "Buttons", "Job Listings Section"], "preview": "https://cdn.prod.website-files.com/61789b489343c8242282a0ae/61f91cab5233c448a1a64b73_61f91a0626437087ff137956_image-career9.png"},
        {"slug": "section_career10", "name": "Career 10", "tags": ["1 Column", "Text Align Center", "Text Align Left", "Buttons", "Icons", "Job Listings Section"], "preview": "https://cdn.prod.website-files.com/61789b489343c8242282a0ae/61f9151f0ba1b9bf1bf2c38d_section-career10.png"},
        {"slug": "section_career11", "name": "Career 11", "tags": ["1 Column", "Text Align Left", "Buttons", "Icons", "Job Listings Section"], "preview": "https://cdn.prod.website-files.com/61789b489343c8242282a0ae/61f91520296b91b45505b603_section-career11.png"},
        {"slug": "section_career12", "name": "Career 12", "tags": ["2 Columns", "Text Align Left", "Buttons", "Icons", "Job Listings Section"], "preview": "https://cdn.prod.website-files.com/61789b489343c8242282a0ae/61f915212643706b64135fc3_section-career12.png"},
        {"slug": "section_career13", "name": "Career 13", "tags": ["1 Column", "Text Align Center", "Text Align Left", "Buttons", "Icons", "Job Listings Section"], "preview": "https://cdn.prod.website-files.com/61789b489343c8242282a0ae/61f915232c3842017d07c196_section-career13.png"},
        {"slug": "section_career14", "name": "Career 14", "tags": ["1 Column", "Text Align Left", "Buttons", "Icons", "Job Listings Section"], "preview": "https://cdn.prod.website-files.com/61789b489343c8242282a0ae/61f91525ed3c140b3c196fdc_section-career14.png"},
        {"slug": "section_career15", "name": "Career 15", "tags": ["2 Columns", "Text Align Left", "Buttons", "Icons", "Job Listings Section"], "preview": "https://cdn.prod.website-files.com/61789b489343c8242282a0ae/61f91527bfcebdf1d811359b_section-career15.png"},
        {"slug": "section_career16", "name": "Career 16", "tags": ["1 Column", "Text Align Center", "Text Align Left", "Icons", "Job Listings Section"], "preview": "https://cdn.prod.website-files.com/61789b489343c8242282a0ae/61f91528a1ae550e42ae8bf3_section-career16.png"},
        {"slug": "section_career17", "name": "Career 17", "tags": ["1 Column", "Text Align Center", "Icons", "Job Listings Section"], "preview": "https://cdn.prod.website-files.com/61789b489343c8242282a0ae/61f9152905e55281d5253ec9_section-career17.png"},
        {"slug": "section_career18", "name": "Career 18", "tags": ["2 Columns", "Text Align Left", "Icons", "Job Listings Section"], "preview": "https://cdn.prod.website-files.com/61789b489343c8242282a0ae/61f9152cf2347a4465548c97_section-career18.png"},
        {"slug": "section_career19", "name": "Career 19", "tags": ["1 Column", "Text Align Left", "Text Align Center", "Buttons", "Icons", "Tabs"], "preview": "https://cdn.prod.website-files.com/61789b489343c8242282a0ae/621db0069dfbda8522781d57_61f93374f8f7f8e62e7e341e_image-career19.png"},
        {"slug": "section_career20", "name": "Career 20", "tags": ["1 Column", "Text Align Left", "Buttons", "Icons", "Tabs", "Job Listings Section"], "preview": "https://cdn.prod.website-files.com/61789b489343c8242282a0ae/61f9152ef3cc806ed6574434_section-career20.png"},
        {"slug": "section_career21", "name": "Career 21", "tags": ["2 Columns", "Text Align Left", "Buttons", "Icons", "Tabs", "Job Listings Section"], "preview": "https://cdn.prod.website-files.com/61789b489343c8242282a0ae/61f915308967ff8a3cd920ea_section-career21.png"},
        {"slug": "section_career22", "name": "Career 22", "tags": ["2 Columns", "Text Align Left", "Text Align Center", "Buttons", "Icons", "Job Listings Section"], "preview": "https://cdn.prod.website-files.com/61789b489343c8242282a0ae/61f91531d3656b7a1617bb74_section-career22.png"},
        {"slug": "section_career23", "name": "Career 23", "tags": ["2 Columns", "Text Align Left", "Text Align Center", "Buttons", "Icons", "Job Listings Section"], "preview": "https://cdn.prod.website-files.com/61789b489343c8242282a0ae/61f9153384701465a75bf8d2_section-career23.png"},
        {"slug": "section_career24", "name": "Career 24", "tags": ["1 Column", "Text Align Center", "Text Align Left", "Buttons", "Icons", "Job Listings Section"], "preview": "https://cdn.prod.website-files.com/61789b489343c8242282a0ae/61f915344e6343057805c3b3_section-career24.png"},
        {"slug": "section_career25", "name": "Career 25", "tags": ["2 Columns", "Text Align Left", "Text Align Center", "Buttons", "Icons", "Job Listings Section"], "preview": "https://cdn.prod.website-files.com/61789b489343c8242282a0ae/61f91536b6f2a6001693ba3b_section-career25.png"},
        {"slug": "section_career26", "name": "Career 26", "tags": ["2 Columns", "Text Align Left", "Text Align Center", "Image/Video Right", "Buttons", "Icons"], "preview": "https://cdn.prod.website-files.com/61789b489343c8242282a0ae/61f91537877dbcc274603056_section-career26.png"},
        {"slug": "section_career27", "name": "Career 27", "tags": ["2 Columns", "Text Align Left", "Text Align Center", "Image/Video Right", "Buttons", "Icons"], "preview": "https://cdn.prod.website-files.com/61789b489343c8242282a0ae/61f91538c095abda74e942f4_section-career27.png"}
      ]
    },
    {
      "slug": "gallery-sections",
      "name": "Gallery Sections",
      "components": [
        {"slug": "section_gallery25", "name": "Gallery 25", "tags": ["2 Columns", "Text Align Left", "Image/Video Right", "Multiple Images", "Image Lightbox", "Image"], "preview": "https://cdn.prod.website-files.com/61789b489343c8242282a0ae/679f25feb8d7389296f71824_section_gallery25.png"},
        {"slug": "section_gallery27", "name": "Gallery 27", "tags": ["2 Columns", "Text Align Left", "Image/Video Right", "Multiple Images", "Image Lightbox", "Image"], "preview": "https://cdn.prod.website-files.com/61789b489343c8242282a0ae/679f25feda3dcdeafa2799f6_section_gallery27.png"},
        {"slug": "section_gallery26", "name": "Gallery 26", "tags": ["2 Columns", "Text Align Left", "Image/Video Right", "Multiple Images", "Image Lightbox", "Image"], "preview": "https://cdn.prod.website-files.com/61789b489343c8242282a0ae/679f25fe854da207536ff762_section_gallery26.png"},
        {"slug": "section_gallery1", "name": "Gallery 1", "tags": ["1 Column", "Text Align Center", "Image Lightbox", "Gallery Section"], "preview": "https://cdn.prod.website-files.com/61789b489343c8242282a0ae/61f915399fe712a7bd203cec_section-gallery1.png"},
        {"slug": "section_gallery2", "name": "Gallery 2", "tags": ["2 Columns", "Text Align Center", "Image Lightbox", "Multiple Images", "Image", "Gallery Section"], "preview": "https://cdn.prod.website-files.com/61789b489343c8242282a0ae/61f9153bf3aaa38cf1a58f28_section-gallery2.png"},
        {"slug": "section_gallery3", "name": "Gallery 3", "tags": ["3 Columns", "Text Align Center", "Image Lightbox", "Multiple Images", "Image", "Gallery Section"], "preview": "https://cdn.prod.website-files.com/61789b489343c8242282a0ae/61f9153ca4ffe1aa3b876e8e_section-gallery3.png"},
        {"slug": "section_gallery4", "name": "Gallery 4", "tags": ["4 Columns", "Text Align Center", "Image Lightbox", "Multiple Images", "Image", "Gallery Section"], "preview": "https://cdn.prod.website-files.com/61789b489343c8242282a0ae/61f9153db4ef1f01ca018874_section-gallery4.png"},
        {"slug": "section_gallery5", "name": "Gallery 5", "tags": ["3 Columns", "Text Align Center", "Image Lightbox", "Multiple Images", "Image", "Gallery Section"], "preview": "https://cdn.prod.website-files.com/61789b489343c8242282a0ae/61f9153fd10f1f9b5a6691fe_section-gallery5.png"},
        {"slug": "section_gallery6", "name": "Gallery 6", "tags": ["4 Columns", "Text Align Center", "Image Lightbox", "Multiple Images", "Image", "Gallery Section"], "preview": "https://cdn.prod.website-files.com/61789b489343c8242282a0ae/61f91540b71e0f1360f07d62_section-gallery6.png"},
        {"slug": "section_gallery7", "name": "Gallery 7", "tags": ["2 Columns", "Text Align Center", "Image Lightbox", "Multiple Images", "Image", "Gallery Section"], "preview": "https://cdn.prod.website-files.com/61789b489343c8242282a0ae/61f91541a1ae557973ae8cb1_section-gallery7.png"},
        {"slug": "section_gallery8", "name": "Gallery 8", "tags": ["2 Columns", "Text Align Center", "Image Lightbox", "Multiple Images", "Image", "Gallery Section"], "preview": "https://cdn.prod.website-files.com/61789b489343c8242282a0ae/61f915421c3de782d4c14f50_section-gallery8.png"},
        {"slug": "section_gallery9", "name": "Gallery 9", "tags": ["3 Columns", "Text Align Center", "Image Lightbox", "Multiple Images", "Image", "Gallery Section"], "preview": "https://cdn.prod.website-files.com/61789b489343c8242282a0ae/61f91544d90359414ec06657_section-gallery9.png"},
        {"slug": "section_gallery10", "name": "Gallery 10", "tags": ["3 Columns", "Text Align Center", "Image Lightbox", "Multiple Images", "Image", "Gallery Section"], "preview": "https://cdn.prod.website-files.com/61789b489343c8242282a0ae/61f915452252d047f8d0f140_section-gallery10.png"},
        {"slug": "section_gallery11", "name": "Gallery 11", "tags": ["2 Columns", "Text Align Center", "Image Lightbox", "Multiple Images", "Image", "Gallery Section"], "preview": "https://cdn.prod.website-files.com/61789b489343c8242282a0ae/61f9154653e50c2823930751_section-gallery11.png"},
        {"slug": "section_gallery12", "name": "Gallery 12", "tags": ["2 Columns", "Text Align Center", "Image Lightbox", "Multiple Images", "Image", "Gallery Section"], "preview": "https://cdn.prod.website-files.com/61789b489343c8242282a0ae/61f91548f2347a2538548d0a_section-gallery12.png"},
        {"slug": "section_gallery13", "name": "Gallery 13", "tags": ["1 Column", "Text Align Center", "Image Lightbox", "Multiple Images", "Slider", "Image"], "preview": "https://cdn.prod.website-files.com/61789b489343c8242282a0ae/61f91549a1ae55ca48ae8cc5_section-gallery13.png"},
        {"slug": "section_gallery14", "name": "Gallery 14", "tags": ["1 Column", "Text Align Center", "Image Lightbox", "Multiple Images", "Slider", "Image"], "preview": "https://cdn.prod.website-files.com/61789b489343c8242282a0ae/61f9154a87c361af1d9b7659_section-gallery14.png"},
        {"slug": "section_gallery15", "name": "Gallery 15", "tags": ["1 Column", "Text Align Center", "Image Lightbox", "Multiple Images", "Slider", "Image"], "preview": "https://cdn.prod.website-files.com/61789b489343c8242282a0ae/61f9154cc095ab720fe94330_section-gallery15.png"},
        {"slug": "section_gallery16", "name": "Gallery 16", "tags": ["2 Columns", "Text Align Center", "Image Lightbox", "Multiple Images", "Slider", "Image"], "preview": "https://cdn.prod.website-files.com/61789b489343c8242282a0ae/61f9154dc095ab419ce94339_section-gallery16.png"},
        {"slug": "section_gallery17", "name": "Gallery 17", "tags": ["2 Columns", "Text Align Center", "Image Lightbox", "Multiple Images", "Slider", "Image"], "preview": "https://cdn.prod.website-files.com/61789b489343c8242282a0ae/61f9154fbe4f0e06d5bd8971_section-gallery17.png"},
        {"slug": "section_gallery18", "name": "Gallery 18", "tags": ["3 Columns", "Text Align Center", "Image Lightbox", "Multiple Images", "Slider", "Image"], "preview": "https://cdn.prod.website-files.com/61789b489343c8242282a0ae/61f91550f3cc80eb03574531_section-gallery18.png"},
        {"slug": "section_gallery19", "name": "Gallery 19", "tags": ["4 Columns", "Text Align Center", "Image Lightbox", "Multiple Images", "Slider", "Image"], "preview": "https://cdn.prod.website-files.com/61789b489343c8242282a0ae/61f915517224662da2e3f4f5_section-gallery19.png"},
        {"slug": "section_gallery20", "name": "Gallery 20", "tags": ["1 Column", "Text Align Left", "Image Lightbox", "Multiple Images", "Slider", "Image"], "preview": "https://cdn.prod.website-files.com/61789b489343c8242282a0ae/61f91552296f25a769a33921_section-gallery20.png"},
        {"slug": "section_gallery21", "name": "Gallery 21", "tags": ["2 Columns", "Text Align Left", "Image Lightbox", "Multiple Images", "Slider", "Image"], "preview": "https://cdn.prod.website-files.com/61789b489343c8242282a0ae/61f9155452b04767cdf1c583_section-gallery21.png"},
        {"slug": "section_gallery22", "name": "Gallery 22", "tags": ["3 Columns", "Text Align Left", "Image Lightbox", "Multiple Images", "Slider", "Image"], "preview": "https://cdn.prod.website-files.com/61789b489343c8242282a0ae/61f915554e634347ef05c4ea_section-gallery22.png"},
        {"slug": "section_gallery23", "name": "Gallery 23", "tags": ["Text Align Left", "4 Columns", "Image Lightbox", "Multiple Images", "Slider", "Image"], "preview": "https://cdn.prod.website-files.com/61789b489343c8242282a0ae/61f9155619c4c46893877d8f_section-gallery23.png"},
        {"slug": "section_gallery24", "name": "Gallery 24", "tags": ["Text Align Center", "1 Column", "Image Lightbox", "Multiple Images", "Image", "Gallery Section"], "preview": "https://cdn.prod.website-files.com/61789b489343c8242282a0ae/68e5a5f152037de031faddee_Gallery24.gif"}
      ]
    },
    {
      "slug": "contact-modals",
      "name": "Contact Modals",
      "components": [
        {"slug": "section_contact-modal1", "name": "Contact Modal 1", "tags": ["Text Align Center", "1 Column", "Form", "Modal"], "preview": "https://cdn.prod.website-files.com/61789b489343c8242282a0ae/624ad7db39fb1e296050a0ee_621dbfa29d6c5b7696987548_image-contact-modal1.png"},
        {"slug": "section_contact-modal2", "name": "Contact Modal 2", "tags": ["Text Align Center", "1 Column", "Form", "Modal"], "preview": "https://cdn.prod.website-files.com/61789b489343c8242282a0ae/624ad7dcf8a7c0c1e16ffb58_621dbfad3daaa8d38524734d_image-contact-modal2.png"},
        {"slug": "section_contact-modal3", "name": "Contact Modal 3", "tags": ["Text Align Center", "1 Column", "Form", "Modal"], "preview": "https://cdn.prod.website-files.com/61789b489343c8242282a0ae/624ad7dec69acf933fbd35b2_621dbfb7a7ca99a2aab0d5d6_image-contact-modal3.png"},
        {"slug": "section_contact-modal4", "name": "Contact Modal 4", "tags": ["Text Align Center", "1 Column", "Form", "Modal"], "preview": "https://cdn.prod.website-files.com/61789b489343c8242282a0ae/624ad7de1be6a2ee30d88817_621dbfc0b62c8631024f1a9a_image-contact-modal4.png"},
        {"slug": "section_contact-modal5", "name": "Contact Modal 5", "tags": ["Text Align Center", "1 Column", "Form", "Modal"], "preview": "https://cdn.prod.website-files.com/61789b489343c8242282a0ae/624ad7e0654c01f072ef3924_621dbfcab62c862b914f1aab_image-contact-modal5.png"},
        {"slug": "section_contact-modal6", "name": "Contact Modal 6", "tags": ["Text Align Center", "1 Column", "Form", "Modal"], "preview": "https://cdn.prod.website-files.com/61789b489343c8242282a0ae/624ad7e18d6696b9ea5cf37f_621dbfd4ad76d537b9a27162_image-contact-modal6.png"}
      ]
    },
    {
      "slug": "banners",
      "name": "Banners",
      "components": [
        {"slug": "section_banner15", "name": "Banner 15", "tags": ["Text Align Center", "Image"], "preview": "https://cdn.prod.website-files.com/61789b489343c8242282a0ae/68e5a25ee7f3f0e46f5dd81a_Banner15.gif"},
        {"slug": "section_banner16", "name": "Banner 16", "tags": ["Text Align Center", "Image"], "preview": "https://cdn.prod.website-files.com/61789b489343c8242282a0ae/68e5a57b26e8bd001573ebda_Banner16.gif"},
        {"slug": "banner1_component", "name": "Banner 1", "tags": ["Text Align Left", "Icons", "Newsletter Sign Up", "Announcement Banner"], "preview": "https://cdn.prod.website-files.com/61789b489343c8242282a0ae/624ad73f1be6a28da3d886d0_621dbf64ecf4fc30d09afe99_image-banner1.png"},
        {"slug": "banner10_component", "name": "Banner 10", "tags": ["Text Align Center", "Text Only", "Marquee Banner"], "preview": "https://cdn.prod.website-files.com/61789b489343c8242282a0ae/621da3348c92ca004bb1cc8a_banner10_component.png"},
        {"slug": "banner2_component", "name": "Banner 2", "tags": ["Text Align Left", "Icons", "Buttons", "Announcement Banner"], "preview": "https://cdn.prod.website-files.com/61789b489343c8242282a0ae/624ad740876f54f341d538e0_621dbf7284d5871542ca8221_image-banner2.png"},
        {"slug": "banner3_component", "name": "Banner 3", "tags": ["Text Align Left", "Icons", "Buttons", "Announcement Banner"], "preview": "https://cdn.prod.website-files.com/61789b489343c8242282a0ae/624ad74072aee70df5474ab0_621dbf7becc70bde14d4011d_image-banner3.png"},
        {"slug": "banner4_component", "name": "Banner 4", "tags": ["Text Align Left", "Icons", "Buttons", "Announcement Banner"], "preview": "https://cdn.prod.website-files.com/61789b489343c8242282a0ae/624ad741654c015fd1eed35b_621dbf86e9df18ef2115bdd9_image-banner4.png"},
        {"slug": "banner5_component", "name": "Banner 5", "tags": ["Text Align Center", "Text Only", "Announcement Banner"], "preview": "https://cdn.prod.website-files.com/61789b489343c8242282a0ae/624ad74246db42eefaaab6d5_621dbf93ecf4fcbd0c9b0121_image-banner5.png"},
        {"slug": "banner6_component", "name": "Banner 6", "tags": ["Text Align Left", "Icons", "Newsletter Sign Up", "Announcement Banner"], "preview": "https://cdn.prod.website-files.com/61789b489343c8242282a0ae/621da339e2461b056ec0d4e5_banner6_component.png"},
        {"slug": "banner7_component", "name": "Banner 7", "tags": ["Text Align Left", "Icons", "Buttons", "Announcement Banner"], "preview": "https://cdn.prod.website-files.com/61789b489343c8242282a0ae/621da33a83229fa5a55441a7_banner7_component.png"},
        {"slug": "banner8_component", "name": "Banner 8", "tags": ["Text Align Left", "Icons", "Buttons", "Announcement Banner"], "preview": "https://cdn.prod.website-files.com/61789b489343c8242282a0ae/621da33bc0919eb7822c2d3f_banner8_component.png"},
        {"slug": "banner9_component", "name": "Banner 9", "tags": ["Text Align Left", "Icons", "Buttons", "Announcement Banner"], "preview": "https://cdn.prod.website-files.com/61789b489343c8242282a0ae/621da33d4da79c91ea97d285_banner9_component.png"},
        {"slug": "section_banner12", "name": "Banner 12", "tags": ["Text Align Center", "Text Only", "Marquee Banner"], "preview": "https://cdn.prod.website-files.com/61789b489343c8242282a0ae/68e5a09aae648d0bcd5922c5_Banner12.gif"},
        {"slug": "section_banner11", "name": "Banner 11", "tags": ["Text Align Center", "Text Only", "Marquee Banner"], "preview": "https://cdn.prod.website-files.com/61789b489343c8242282a0ae/68e5a0d08ba075b20d1259c5_Banner11.gif"},
        {"slug": "section_banner13", "name": "Banner 13", "tags": ["Text Align Center", "Text Only", "Marquee Banner"], "preview": "https://cdn.prod.website-files.com/61789b489343c8242282a0ae/68e5a568b8df9ae075a1654f_Banner13.gif"},
        {"slug": "section_banner14", "name": "Banner 14", "tags": ["Text Align Center", "Text Only", "Marquee Banner"], "preview": "https://cdn.prod.website-files.com/61789b489343c8242282a0ae/68e5a508ae648d0bcd593b29_Banner14.gif"}
      ]
    },
    {
      "slug": "portfolio-headers",
      "name": "Portfolio Headers",
      "components": [
        {"slug": "section_portfolio-header6", "name": "Portfolio Header 6", "tags": ["2 Columns", "Text Align Left", "Image/Video Top", "Image", "Portfolio Item Header Section", "Project Item Header Section"], "preview": "https://cdn.prod.website-files.com/61789b489343c8242282a0ae/640532fc0d34779ff64001ff_section_portfolio-header6.png"},
        {"slug": "section_portfolio-header12", "name": "Portfolio Header 12", "tags": ["2 Columns", "Text Align Left", "Image/Video Center", "Background Image", "Portfolio Item Header Section", "Project Item Header Section"], "preview": "https://cdn.prod.website-files.com/61789b489343c8242282a0ae/6426649656cc4bebe407f026_kI52_loRduWjXql-zst1xrI_bBUERFgfMXye2FZXJfU.png"},
        {"slug": "section_portfolio-header1", "name": "Portfolio Header 1", "tags": ["1 Column", "Text Align Center", "Text Only", "Portfolio Item Header Section", "Project Item Header Section"], "preview": "https://cdn.prod.website-files.com/61789b489343c8242282a0ae/640532fc4011216e2e996424_section_portfolio-header1.png"},
        {"slug": "section_portfolio-header7", "name": "Portfolio Header 7", "tags": ["2 Columns", "Text Align Left", "Image/Video Bottom", "Image", "Portfolio Item Header Section", "Project Item Header Section"], "preview": "https://cdn.prod.website-files.com/61789b489343c8242282a0ae/640532fca05a6bfe9268159c_section_portfolio-header7.png"},
        {"slug": "section_portfolio-header10", "name": "Portfolio Header 10", "tags": ["2 Columns", "Text Align Left", "Image/Video Top", "Image", "Portfolio Item Header Section", "Project Item Header Section"], "preview": "https://cdn.prod.website-files.com/61789b489343c8242282a0ae/640532fc1122c6358ec2f47a_section_portfolio-header10.png"},
        {"slug": "section_portfolio-header2", "name": "Portfolio Header 2", "tags": ["1 Column", "Text Align Center", "Image/Video Top", "Image", "Portfolio Item Header Section", "Project Item Header Section"], "preview": "https://cdn.prod.website-files.com/61789b489343c8242282a0ae/640532fd156eb11a19cd6d81_section_portfolio-header2.png"},
        {"slug": "section_portfolio-header11", "name": "Portfolio Header 11", "tags": ["2 Columns", "Text Align Left", "Image/Video Bottom", "Image", "Portfolio Item Header Section", "Project Item Header Section"], "preview": "https://cdn.prod.website-files.com/61789b489343c8242282a0ae/640532fd0d3477953c400206_section_portfolio-header11.png"},
        {"slug": "section_portfolio-header3", "name": "Portfolio Header 3", "tags": ["1 Column", "Text Align Center", "Image/Video Bottom", "Image", "Portfolio Item Header Section", "Project Item Header Section"], "preview": "https://cdn.prod.website-files.com/61789b489343c8242282a0ae/640532fd0d3477439a40020a_section_portfolio-header3.png"},
        {"slug": "section_portfolio-header4", "name": "Portfolio Header 4", "tags": ["1 Column", "Text Align Center", "Image/Video Center", "Background Image", "Portfolio Item Header Section", "Project Item Header Section"], "preview": "https://cdn.prod.website-files.com/61789b489343c8242282a0ae/6426648eadefaf294542e0c0_b7LkXs5nvIPsUb_ySqEllAGkSm2oo-8xBUNkmkq91_A.png"},
        {"slug": "section_portfolio-header9", "name": "Portfolio Header 9", "tags": ["2 Columns", "Text Align Left", "Text Only", "Portfolio Item Header Section", "Project Item Header Section"], "preview": "https://cdn.prod.website-files.com/61789b489343c8242282a0ae/640532fd7d01f7841442f7a1_section_portfolio-header9.png"},
        {"slug": "section_portfolio-header8", "name": "Portfolio Header 8", "tags": ["2 Columns", "Text Align Left", "Image/Video Center", "Background Image", "Portfolio Item Header Section", "Project Item Header Section"], "preview": "https://cdn.prod.website-files.com/61789b489343c8242282a0ae/64266492875e6a3ddee6f1d2_5dHBmB7z1pZK1J4HoqeI5Uel1vPtPcFj-j1HRq-WK30.png"},
        {"slug": "section_portfolio-header5", "name": "Portfolio Header 5", "tags": ["2 Columns", "Text Align Left", "Text Only", "Portfolio Item Header Section", "Project Item Header Section"], "preview": "https://cdn.prod.website-files.com/61789b489343c8242282a0ae/640532fd4b572623669b4134_section_portfolio-header5.png"}
      ]
    }
  ]
}
